Metadata-Version: 2.1
Name: pytest-notion
Version: 1.0.1
Summary: A PyTest Reporter to send test runs to Notion.so
Home-page: https://github.com/Gimpneek/notion-pytest-reporter
Author: Colin Wren
Author-email: gimpneek@gmail.com
License: GPLv3
Keywords: notion pytest reporter
Platform: UNKNOWN
Classifier: Framework :: Pytest
Classifier: Operating System :: Microsoft :: Windows
Classifier: Operating System :: MacOS :: MacOS X
Classifier: Operating System :: POSIX
Classifier: Operating System :: Unix
Classifier: Programming Language :: Python
Classifier: Programming Language :: Python :: 2
Classifier: Programming Language :: Python :: 2.7
Classifier: Programming Language :: Python :: 3
Classifier: Programming Language :: Python :: 3.4
Classifier: Programming Language :: Python :: 3.5
Classifier: Programming Language :: Python :: 3.6
Classifier: Programming Language :: Python :: 3.7
Classifier: Programming Language :: Python :: Implementation :: CPython
Classifier: Programming Language :: Python :: Implementation :: PyPy
Classifier: License :: OSI Approved :: GNU General Public License (GPL)
Provides-Extra: test
